toolmate/README.md
toolmate/ToolMateAI.py
toolmate/__init__.py
toolmate/api_client.py
toolmate/api_server.py
toolmate/autoassist.py
toolmate/autobuild.py
toolmate/autocaptain.py
toolmate/autoretrieve.py
toolmate/captainagent_expert_library.json
toolmate/chatgpt.py
toolmate/check_on_android.txt
toolmate/codey.py
toolmate/commandprompt.py
toolmate/config.py
toolmate/eTextEdit.py
toolmate/geminipro.py
toolmate/geminiprovision.py
toolmate/groqchat.py
toolmate/llamacpp.py
toolmate/llamacppserver.py
toolmate/main.py
toolmate/mistralchat.py
toolmate/ollamachat.py
toolmate/package_name.txt
toolmate/palm2.py
toolmate/qt.py
toolmate/rag.py
toolmate/requirements.txt
toolmate/requirements_disabled_in_lite.txt
toolmate/requirements_for_checking.txt
toolmate/requirements_lite.txt
toolmate/requirements_lite_old.txt
toolmate/servers.py
toolmate/setup.py
toolmate/audio/notification1.mp3
toolmate/audio/notification1_mild.mp3
toolmate/audio/notification2.mp3
toolmate/audio/notification2_mild.mp3
toolmate/docs/Action Menu.md
toolmate/docs/Additional Chat Model.md
toolmate/docs/Android Versions.md
toolmate/docs/Anthropic API Setup.md
toolmate/docs/AutoGen Integration.md
toolmate/docs/Azure API Setup.md
toolmate/docs/Beyond LetMeDoItAI.md
toolmate/docs/CLI Options.md
toolmate/docs/Change AI Backends and Models.md
toolmate/docs/Chat Record Management.md
toolmate/docs/Configure Ollama Server.md
toolmate/docs/Custom System Messages.md
toolmate/docs/Customise Assistant Name.md
toolmate/docs/Docker Setup on Android Termux.md
toolmate/docs/Download LLM in GGUF Format.md
toolmate/docs/Edit Config Manually.md
toolmate/docs/Edit Current Conversation.md
toolmate/docs/Examples.md
toolmate/docs/Fabric Integration.md
toolmate/docs/First launch.md
toolmate/docs/Function Call Approach with Any LLMs.md
toolmate/docs/GPU Acceleration with Llama_cpp server.md
toolmate/docs/GPU Acceleration.md
toolmate/docs/GUI.md
toolmate/docs/Gemini.md
toolmate/docs/Github API Setup.md
toolmate_lite-0.6.51.dist-info/METADATA
toolmate_lite-0.6.51.dist-info/WHEEL
toolmate_lite-0.6.51.dist-info/entry_points.txt
toolmate_lite-0.6.51.dist-info/top_level.txt
toolmate_lite-0.6.51.dist-info/RECORD
