Metadata-Version: 2.2
Name: toolmate_lite
Version: 0.6.51
Summary: ToolMate AI, developed by Eliran Wong, is a cutting-edge AI companion that seamlessly integrates agents, tools, and plugins to excel in conversations, generative work, and task execution. Supports custom workflow and plugins to automate multi-step actions.
Home-page: https://toolmate.ai
Author: Eliran Wong
Author-email: support@toolmate.ai
License: GNU General Public License (GPL)
Project-URL: Source, https://github.com/eliranwong/toolmate
Project-URL: Tracker, https://github.com/eliranwong/toolmate/issues
Project-URL: Documentation, https://github.com/eliranwong/toolmate/wiki
Project-URL: Funding, https://www.paypal.me/toolmate
Keywords: ai assistant ollama llama llamacpp groq openai chatgpt gemini autogen rag agent stable-diffusion fabric dalle imagen
Classifier: Development Status :: 5 - Production/Stable
Classifier: Intended Audience :: End Users/Desktop
Classifier: Topic :: Utilities
Classifier: Topic :: Scientific/Engineering :: Artificial Intelligence
Classifier: Topic :: Software Development :: Build Tools
Classifier: License :: OSI Approved :: GNU General Public License v3 or later (GPLv3+)
Classifier: Programming Language :: Python :: 3.8
Classifier: Programming Language :: Python :: 3.9
Classifier: Programming Language :: Python :: 3.10
Classifier: Programming Language :: Python :: 3.11
Classifier: Programming Language :: Python :: 3.12
Requires-Python: >=3.8, <3.13
Requires-Dist: numpy==1.26.4
Requires-Dist: pandas==2.2.3
Requires-Dist: protobuf==4.25.3
Requires-Dist: ollama==0.4.7
Requires-Dist: groq==0.15.0
Requires-Dist: mistralai==1.4.0
Requires-Dist: openai==1.60.0
Requires-Dist: tiktoken==0.8.0
Requires-Dist: anthropic==0.45.0
Requires-Dist: huggingface-hub==0.27.1
Requires-Dist: langchain==0.3.15
Requires-Dist: langchain-community==0.3.15
Requires-Dist: langchain-core==0.3.31
Requires-Dist: langchain-openai==0.3.2
Requires-Dist: langchain-ollama==0.2.2
Requires-Dist: langchain-text-splitters==0.3.5
Requires-Dist: langsmith==0.3.1
Requires-Dist: kiwisolver==1.4.7
Requires-Dist: termcolor==2.5.0
Requires-Dist: wcwidth==0.2.13
Requires-Dist: aiosignal==1.3.1
Requires-Dist: aiohappyeyeballs==2.4.4
Requires-Dist: annotated-types==0.7.0
Requires-Dist: exceptiongroup==1.2.2
Requires-Dist: h11==0.14.0
Requires-Dist: cachetools==5.5.0
Requires-Dist: marshmallow==3.23.1
Requires-Dist: httplib2==0.22.0
Requires-Dist: frozenlist==1.5.0
Requires-Dist: sqlmodel==0.0.22
Requires-Dist: tabulate==0.9.0
Requires-Dist: xlrd==2.0.1
Requires-Dist: humanfriendly==10.0
Requires-Dist: httptools==0.6.4
Requires-Dist: joblib==1.4.2
Requires-Dist: matplotlib==3.9.3
Requires-Dist: matplotlib-inline==0.1.7
Requires-Dist: importlib_metadata==8.4.0
Requires-Dist: jedi==0.19.2
Requires-Dist: wikipedia==1.4.0
Requires-Dist: xyzservices==2024.9.0
Requires-Dist: zope.interface==7.0.3
Requires-Dist: blinker==1.9.0
Requires-Dist: deepdiff==8.0.1
Requires-Dist: itsdangerous==2.2.0
Requires-Dist: imageio==2.35.1
Requires-Dist: multitasking==0.0.11
Requires-Dist: lazy-loader==0.4
Requires-Dist: soundfile==0.12.1
Requires-Dist: sounddevice==0.5.0
Requires-Dist: elevenlabs==1.5.0
Requires-Dist: wheel
Requires-Dist: setuptools
Requires-Dist: pipdeptree
Requires-Dist: googlesearch-python
Requires-Dist: requests
Requires-Dist: argparse
Requires-Dist: folium
Requires-Dist: sympy
Requires-Dist: prompt_toolkit
Requires-Dist: Pygments
Requires-Dist: datetime
Requires-Dist: geocoder
Requires-Dist: art
Requires-Dist: gTTS
Requires-Dist: yt-dlp
Requires-Dist: qrcode
Requires-Dist: pyperclip
Requires-Dist: colorama
Requires-Dist: pillow
Requires-Dist: einops
Requires-Dist: python-magic
Requires-Dist: feedparser
Requires-Dist: html2text
Requires-Dist: pypdf
Requires-Dist: setuptools-rust
Requires-Dist: SpeechRecognition
Requires-Dist: pydub
Requires-Dist: pytz
Requires-Dist: geopy
Requires-Dist: psutil
Requires-Dist: flashtext
Requires-Dist: wikipedia
Requires-Dist: tqdm
Requires-Dist: edge-tts
Requires-Dist: ftfy
Requires-Dist: fastapi
Requires-Dist: uvicorn
Requires-Dist: xonsh[full]
Requires-Dist: markitdown
Requires-Dist: pyautogui
Provides-Extra: bible
Requires-Dist: uniquebible>=0.2.16; extra == "bible"
Dynamic: author
Dynamic: author-email
Dynamic: classifier
Dynamic: description
Dynamic: home-page
Dynamic: keywords
Dynamic: license
Dynamic: project-url
Dynamic: provides-extra
Dynamic: requires-dist
Dynamic: requires-python
Dynamic: summary
